setup.py
ancypwn_terminal_termite.egg-info/PKG-INFO
ancypwn_terminal_termite.egg-info/SOURCES.txt
ancypwn_terminal_termite.egg-info/dependency_links.txt
ancypwn_terminal_termite.egg-info/top_level.txt
src/__init__.py
src/termite.py