Metadata-Version: 1.0
Name: ancypwn-terminal-termite
Version: 0.0.1
Summary: ancypwn terminal plugin
Home-page: https://github.com/circleous/ancypwn-terminal-termite
Author: circleous
Author-email: circleousdev@gmail.com
License: UNKNOWN
Platform: UNKNOWN
